assumphelper/__init__.py
assumphelper/check.py
assumphelper/exceptions.py
assumphelper/homoscedasticity.py
assumphelper/hypothesis.py
assumphelper/independence.py
assumphelper/linearity.py
assumphelper/normality.py
assumphelper/utilities.py
assumphelper-0.2.0.dist-info/METADATA
assumphelper-0.2.0.dist-info/WHEEL
assumphelper-0.2.0.dist-info/top_level.txt
assumphelper-0.2.0.dist-info/RECORD
