Metadata-Version: 2.4
Name: assumphelper
Version: 0.2.0
Summary: Linear Regression Assumption Interpretation Guide
Home-page: https://github.com/rodelcoder1/OOP2
Author: Aque, Badilla, Caaminio, Moog, Prollo
Author-email: rodelpellazar1@gmail.com
Classifier: Programming Language :: Python :: 3
Classifier: License :: OSI Approved :: MIT License
Classifier: Operating System :: OS Independent
Requires-Python: >=3.8
Requires-Dist: numpy>=1.24.0
Requires-Dist: pandas>=2.0.0
Requires-Dist: scipy>=1.11.0
Requires-Dist: statsmodels>=0.14.0
Requires-Dist: scikit-learn>=1.3.0
Requires-Dist: matplotlib>=3.8.0
Dynamic: author
Dynamic: author-email
Dynamic: classifier
Dynamic: description
Dynamic: description-content-type
Dynamic: home-page
Dynamic: requires-dist
Dynamic: requires-python
Dynamic: summary
